__init__.py
locate_Path_tmorales/__init__.py
locate_Path_tmorales/locator.py
tests/__init__.py
automationsarasa-0.0.0.dist-info/LICENSE
automationsarasa-0.0.0.dist-info/METADATA
automationsarasa-0.0.0.dist-info/WHEEL
automationsarasa-0.0.0.dist-info/top_level.txt
automationsarasa-0.0.0.dist-info/RECORD
