Metadata-Version: 2.1
Name: automationsarasa
Version: 0.0.0
Summary: demo example
Home-page: https://github.com/moralesveratom/locatePath
Author: tmorales
Author-email: moralesveratomas@gmail.com
License: MIT
Keywords: python,path,locate,locator,pathLocator,pathLocate,locatorPath
Classifier: Development Status :: 1 - Planning
Classifier: Programming Language :: Python :: 3.10
License-File: LICENSE
Requires-Dist: os
Requires-Dist: sys
